xlmcp/__init__.py
xlmcp/config.py
xlmcp/server.py
xlmcp/utils.py
xlmcp/cli/__init__.py
xlmcp/tools/__init__.py
xlmcp/tools/jupyter/__init__.py
xlmcp/tools/jupyter/client.py
xlmcp/tools/jupyter/kernel.py
xlmcp/tools/jupyter/notebook.py
xlmcp/tools/rag/__init__.py
xlmcp/tools/rag/indexer.py
xlmcp/tools/rag/metadata.py
xlmcp/tools/rag/models.py
xlmcp/tools/rag/parsers.py
xlmcp/tools/rag/registry.py
xlmcp/tools/rag/searcher.py
xlmcp/tools/rag/storage.py
xlmcp-0.3.5.dist-info/METADATA
xlmcp-0.3.5.dist-info/WHEEL
xlmcp-0.3.5.dist-info/entry_points.txt
xlmcp-0.3.5.dist-info/licenses/LICENSE
xlmcp-0.3.5.dist-info/RECORD
