Metadata-Version: 2.4
Name: xlmcp
Version: 0.3.5
Summary: MCP server for JupyterHub/Jupyter/Qubx integration with Claude Code
Project-URL: Homepage, https://github.com/xLydianSoftware/aix
Project-URL: Repository, https://github.com/xLydianSoftware/aix
Project-URL: Documentation, https://github.com/xLydianSoftware/aix#readme
Project-URL: Issues, https://github.com/xLydianSoftware/aix/issues
Author-email: Dmitry Marienko <dmitry.ema@gmail.com>
License: MIT
License-File: LICENSE
Keywords: ai,anthropic,claude,jupyter,jupyterhub,mcp,notebook,qubx,xlydian
Classifier: Development Status :: 4 - Beta
Classifier: Intended Audience :: Developers
Classifier: Intended Audience :: Science/Research
Classifier: License :: OSI Approved :: MIT License
Classifier: Operating System :: OS Independent
Classifier: Programming Language :: Python :: 3
Classifier: Programming Language :: Python :: 3.10
Classifier: Programming Language :: Python :: 3.11
Classifier: Programming Language :: Python :: 3.12
Classifier: Topic :: Scientific/Engineering
Classifier: Topic :: Software Development :: Libraries :: Python Modules
Requires-Python: <4.0,>=3.10
Requires-Dist: click>=8.0.0
Requires-Dist: fastmcp>=2.13.0
Requires-Dist: httpx>=0.25.0
Requires-Dist: jupyter-client>=8.0.0
Requires-Dist: llama-index>=0.12.45
Requires-Dist: nbformat>=5.9.0
Requires-Dist: pydantic>=2.0.0
Requires-Dist: pymilvus[milvus-lite,model]>=2.5.11
Requires-Dist: python-dotenv>=1.0.0
Requires-Dist: python-frontmatter>=1.0.0
Requires-Dist: pyyaml>=6.0.0
Requires-Dist: ruff<0.15.0,>=0.14.8
Requires-Dist: rust-just<2.0.0,>=1.44.0
Requires-Dist: toml<0.11.0,>=0.10.2
Requires-Dist: uv<0.10.0,>=0.9.16
Requires-Dist: websockets>=12.0
Provides-Extra: dev
Requires-Dist: pytest-asyncio>=0.21.0; extra == 'dev'
Requires-Dist: pytest>=7.0.0; extra == 'dev'
Requires-Dist: ruff>=0.1.0; extra == 'dev'
